reflex_antd/__init__.py
reflex_antd/base.py
reflex_antd/charts.py
reflex_antd/constant.py
reflex_antd/display.py
reflex_antd/entry.py
reflex_antd/feedback.py
reflex_antd/general.py
reflex_antd/helper.py
reflex_antd/layout.py
reflex_antd/navigation.py
reflex_antd/pro.py
reflex_antd/util.py
reflex_antd/antd/__init__.py
reflex_antd/antd/affix.py
reflex_antd/antd/alert.py
reflex_antd/antd/anchor.py
reflex_antd/antd/auto_complete.py
reflex_antd/antd/avatar.py
reflex_antd/antd/badge.py
reflex_antd/antd/base.py
reflex_antd/antd/breadcrumb.py
reflex_antd/antd/button.py
reflex_antd/antd/calendar.py
reflex_antd/antd/card.py
reflex_antd/antd/carousel.py
reflex_antd/antd/cascader.py
reflex_antd/antd/checkbox.py
reflex_antd/antd/collapse.py
reflex_antd/antd/color_picker.py
reflex_antd/antd/date_picker.py
reflex_antd/antd/descriptions.py
reflex_antd/antd/divider.py
reflex_antd/antd/drawer.py
reflex_antd/antd/dropdown.py
reflex_antd/antd/empty.py
reflex_antd/antd/flex.py
reflex_antd/antd/float_button.py
reflex_antd/antd/form.py
reflex_antd/antd/grid.py
reflex_antd/antd/helper.py
reflex_antd/antd/icon.py
reflex_antd/antd/image.py
reflex_antd/antd/input.py
reflex_antd/antd/input_number.py
reflex_antd/antd/layout.py
reflex_antd/antd/list.py
reflex_antd/antd/mentions.py
reflex_antd/antd/menu.py
reflex_antd/antd/message.py
reflex_antd/antd/modal.py
reflex_antd/antd/notification.py
reflex_antd/antd/pagination.py
reflex_antd/antd/popconfirm.py
reflex_antd/antd/popover.py
reflex_antd/antd/progress.py
reflex_antd/antd/qrcode.py
reflex_antd/antd/radio.py
reflex_antd/antd/rate.py
reflex_antd/antd/result.py
reflex_antd/antd/segmented.py
reflex_antd/antd/select.py
reflex_antd/antd/skeleton.py
reflex_antd/antd/slider.py
reflex_antd/antd/space.py
reflex_antd/antd/spin.py
reflex_antd/antd/splitter.py
reflex_antd/antd/statistic.py
reflex_antd/antd/steps.py
reflex_antd/antd/switch.py
reflex_antd/antd/table.py
reflex_antd/antd/tabs.py
reflex_antd/antd/tag.py
reflex_antd/antd/time_picker.py
reflex_antd-0.2.0.dist-info/licenses/LICENSE
reflex_antd-0.2.0.dist-info/METADATA
reflex_antd-0.2.0.dist-info/WHEEL
reflex_antd-0.2.0.dist-info/top_level.txt
reflex_antd-0.2.0.dist-info/RECORD
