Metadata-Version: 2.4
Name: reflex-antd
Version: 0.2.0
Summary: Reflex custom component ant-design
Author-email: seewind <seewindcn@gmail.com>
License: Apache-2.0
Project-URL: Homepage, https://github.com/seewindcn/reflex-antd
Project-URL: homepage, https://github.com/seewindcn/reflex-antd
Project-URL: source, https://github.com/seewindcn/reflex-antd
Keywords: reflex,reflex-custom-components,ant-design,antd
Classifier: Development Status :: 4 - Beta
Requires-Python: >=3.8
License-File: LICENSE
Requires-Dist: reflex<0.7.0,>=0.6.0
Provides-Extra: dev
Requires-Dist: build; extra == "dev"
Requires-Dist: twine; extra == "dev"
Dynamic: license-file
